google/cloud/workflows/__init__.py
google/cloud/workflows/gapic_version.py
google/cloud/workflows/py.typed
google/cloud/workflows/executions/__init__.py
google/cloud/workflows/executions/gapic_version.py
google/cloud/workflows/executions/py.typed
google/cloud/workflows/executions_v1/__init__.py
google/cloud/workflows/executions_v1/gapic_metadata.json
google/cloud/workflows/executions_v1/gapic_version.py
google/cloud/workflows/executions_v1/py.typed
google/cloud/workflows/executions_v1/services/__init__.py
google/cloud/workflows/executions_v1/services/executions/__init__.py
google/cloud/workflows/executions_v1/services/executions/async_client.py
google/cloud/workflows/executions_v1/services/executions/client.py
google/cloud/workflows/executions_v1/services/executions/pagers.py
google/cloud/workflows/executions_v1/services/executions/transports/__init__.py
google/cloud/workflows/executions_v1/services/executions/transports/base.py
google/cloud/workflows/executions_v1/services/executions/transports/grpc.py
google/cloud/workflows/executions_v1/services/executions/transports/grpc_asyncio.py
google/cloud/workflows/executions_v1/types/__init__.py
google/cloud/workflows/executions_v1/types/executions.py
google/cloud/workflows/executions_v1beta/__init__.py
google/cloud/workflows/executions_v1beta/gapic_metadata.json
google/cloud/workflows/executions_v1beta/gapic_version.py
google/cloud/workflows/executions_v1beta/py.typed
google/cloud/workflows/executions_v1beta/services/__init__.py
google/cloud/workflows/executions_v1beta/services/executions/__init__.py
google/cloud/workflows/executions_v1beta/services/executions/async_client.py
google/cloud/workflows/executions_v1beta/services/executions/client.py
google/cloud/workflows/executions_v1beta/services/executions/pagers.py
google/cloud/workflows/executions_v1beta/services/executions/transports/__init__.py
google/cloud/workflows/executions_v1beta/services/executions/transports/base.py
google_cloud_workflows-1.18.1.dist-info/LICENSE
google_cloud_workflows-1.18.1.dist-info/METADATA
google_cloud_workflows-1.18.1.dist-info/WHEEL
google_cloud_workflows-1.18.1.dist-info/top_level.txt
google_cloud_workflows-1.18.1.dist-info/RECORD
